LICENSE
MANIFEST.in
README.md
requirements.txt
setup.py
bin/archive-subdirectories.py
bin/ftp-downloader.py
pyexeggutor/__init__.py
pyexeggutor.egg-info/PKG-INFO
pyexeggutor.egg-info/SOURCES.txt
pyexeggutor.egg-info/dependency_links.txt
pyexeggutor.egg-info/requires.txt
pyexeggutor.egg-info/top_level.txt