Metadata-Version: 2.4
Name: pyexeggutor
Version: 2025.12.5
Summary: Run shell commands in Python
Home-page: https://github.com/jolespin/pyexeggutor
Author: Josh L. Espinoza
Author-email: jol.espinoz@gmail.com
License: MIT
License-File: LICENSE
Requires-Dist: tqdm
Requires-Dist: memory_profiler
Requires-Dist: loguru
Dynamic: author
Dynamic: author-email
Dynamic: home-page
Dynamic: license
Dynamic: license-file
Dynamic: requires-dist
Dynamic: summary
